Tuchart/Graph.py
Tuchart/__init__.py
Tuchart/__main__.py
Tuchart/__version__.py
Tuchart/layout.py
Tuchart/main.py
tuchart-0.1.2.7.dist-info/DESCRIPTION.rst
tuchart-0.1.2.7.dist-info/METADATA
tuchart-0.1.2.7.dist-info/RECORD
tuchart-0.1.2.7.dist-info/WHEEL
tuchart-0.1.2.7.dist-info/metadata.json
tuchart-0.1.2.7.dist-info/top_level.txt
