Metadata-Version: 2.0
Name: tuchart
Version: 0.1.2.7
Summary: Graphing app for Chinese stocks. 
Home-page: https://github.com/Seedarchangel/TuChart
Author: Rong Zhou Li
Author-email: rzli2@illinois.com
License: MIT
Platform: UNKNOWN
Classifier: License :: OSI Approved :: MIT License
Classifier: Programming Language :: Python
Classifier: Programming Language :: Python :: 2.6
Classifier: Programming Language :: Python :: 2.7
Classifier: Programming Language :: Python :: Implementation :: CPython
Classifier: Programming Language :: Python :: Implementation :: PyPy
Requires-Dist: pyecharts (==0.2.0)
Requires-Dist: qtpy
Requires-Dist: tushare (==0.8.6)
